gitbook_scraper/__init__.py
gitbook_scraper/cli.py
gitbook_scraper/exceptions.py
gitbook_scraper/scraper.py
gitbook_scraper-0.1.1.dist-info/METADATA
gitbook_scraper-0.1.1.dist-info/WHEEL
gitbook_scraper-0.1.1.dist-info/entry_points.txt
gitbook_scraper-0.1.1.dist-info/licenses/LICENSE
gitbook_scraper-0.1.1.dist-info/RECORD
